psyclone/__init__.py
psyclone/alg_gen.py
psyclone/configuration.py
psyclone/docstring_parser.py
psyclone/doxy_main_page.py
psyclone/errors.py
psyclone/expression.py
psyclone/gen_kernel_stub.py
psyclone/generator.py
psyclone/gocean1p0.py
psyclone/kernel_tools.py
psyclone/lfric.py
psyclone/line_length.py
psyclone/profiler.py
psyclone/psyGen.py
psyclone/psyclonefc_cli.py
psyclone/transformations.py
psyclone/utils.py
psyclone/version.py
psyclone/core/__init__.py
psyclone/core/access_sequence.py
psyclone/core/access_type.py
psyclone/core/component_indices.py
psyclone/core/signature.py
psyclone/core/symbolic_maths.py
psyclone/core/variables_access_map.py
psyclone/domain/__init__.py
psyclone/domain/common/__init__.py
psyclone/domain/common/driver_creator.py
psyclone/domain/common/algorithm/__init__.py
psyclone/domain/common/algorithm/psyir.py
psyclone/domain/common/psylayer/__init__.py
psyclone/domain/common/psylayer/psyloop.py
psyclone/domain/common/transformations/__init__.py
psyclone/domain/common/transformations/alg_invoke_2_psy_call_trans.py
psyclone/domain/common/transformations/alg_trans.py
psyclone/domain/common/transformations/kernel_module_inline_trans.py
psyclone/domain/common/transformations/raise_psyir_2_alg_trans.py
psyclone/domain/gocean/__init__.py
psyclone/domain/gocean/go_symbol_table.py
psyclone/domain/gocean/gocean_constants.py
psyclone/domain/gocean/gocean_driver_creator.py
psyclone/domain/gocean/kernel/__init__.py
psyclone/domain/gocean/kernel/psyir.py
psyclone/domain/gocean/transformations/__init__.py
psyclone/domain/gocean/transformations/gocean_alg_invoke_2_psy_call_trans.py
psyclone/domain/gocean/transformations/gocean_const_loop_bounds_trans.py
psyclone/domain/gocean/transformations/gocean_extract_trans.py
psyclone/domain/gocean/transformations/gocean_loop_fuse_trans.py
psyclone/domain/gocean/transformations/gocean_move_iteration_boundaries_inside_kernel_trans.py
psyclone/domain/gocean/transformations/gocean_opencl_trans.py
psyclone-3.2.1.dist-info/licenses/LICENSE
psyclone-3.2.1.dist-info/METADATA
psyclone-3.2.1.dist-info/WHEEL
psyclone-3.2.1.dist-info/top_level.txt
psyclone-3.2.1.dist-info/RECORD
